{
    "こ": [
        "ん",
        "ん"
    ],
    "ん": [
        "に",
        "に",
        "な",
        "な",
        "な",
        "な"
    ],
    "に": [
        "ち",
        "ち",
        "な"
    ],
    "ち": [
        "は",
        "は"
    ],
    "は": [
        null,
        null,
        "？",
        "？",
        "？"
    ],
    "？": [
        null,
        null,
        null,
        null
    ],
    "ふ": [
        "ざ",
        "ざ"
    ],
    "ざ": [
        "け",
        "け",
        "い"
    ],
    "け": [
        "ん",
        "る"
    ],
    "な": [
        "よ",
        "よ",
        "や",
        null,
        null,
        "っ"
    ],
    "よ": [
        null,
        null,
        null
    ],
    "死": [
        "ね",
        "ね"
    ],
    "ね": [
        null,
        null
    ],
    "舐": [
        "め",
        "め",
        "め"
    ],
    "め": [
        "ん",
        "て",
        "ん"
    ],
    "語": [
        "尾"
    ],
    "尾": [
        "と"
    ],
    "と": [
        "ん",
        "う"
    ],
    "や": [
        null
    ],
    "て": [
        "る",
        "お"
    ],
    "る": [
        "？",
        "な"
    ],
    "殺": [
        "す"
    ],
    "す": [
        "よ",
        null,
        "。"
    ],
    "い": [
        "つ",
        "ま"
    ],
    "つ": [
        "も"
    ],
    "も": [
        "お"
    ],
    "お": [
        "世",
        "り"
    ],
    "世": [
        "話"
    ],
    "話": [
        "に"
    ],
    "っ": [
        "て"
    ],
    "り": [
        "ま",
        "が"
    ],
    "ま": [
        "す",
        "す"
    ],
    "あ": [
        "り"
    ],
    "が": [
        "と"
    ],
    "う": [
        "ご"
    ],
    "ご": [
        "ざ"
    ],
    "。": [
        null
    ]
}